[
    {
        "latencies": {
            "total": 232881629,
            "mean": 2328816,
            "50th": 1841104,
            "90th": 3937250,
            "95th": 5346228,
            "99th": 9533875,
            "max": 10981917,
            "min": 978042
        },
        "bytes_in": {
            "total": 18091,
            "mean": 180.91
        },
        "bytes_out": {
            "total": 0,
            "mean": 0
        },
        "earliest": "2025-06-06T00:22:00.315282833+07:00",
        "latest": "2025-06-06T00:22:01.306077083+07:00",
        "end": "2025-06-06T00:22:01.307507583+07:00",
        "duration": 990794250,
        "wait": 1430500,
        "requests": 100,
        "rate": 100.92912832306001,
        "throughput": 100.78361782448987,
        "success": 1,
        "status_codes": {
            "200": 100
        },
        "errors": []
    },
    {
        "latencies": {
            "total": 308180339,
            "mean": 1540901,
            "50th": 1161868,
            "90th": 2802208,
            "95th": 4293624,
            "99th": 7179999,
            "max": 9787333,
            "min": 783500
        },
        "bytes_in": {
            "total": 40400,
            "mean": 202
        },
        "bytes_out": {
            "total": 0,
            "mean": 0
        },
        "earliest": "2025-06-06T00:22:01.313328166+07:00",
        "latest": "2025-06-06T00:22:02.308389791+07:00",
        "end": "2025-06-06T00:22:02.309435291+07:00",
        "duration": 995061625,
        "wait": 1045500,
        "requests": 200,
        "rate": 200.99257671604008,
        "throughput": 200.78161774016024,
        "success": 1,
        "status_codes": {
            "200": 200
        },
        "errors": []
    },
    {
        "latencies": {
            "total": 378403250,
            "mean": 1261344,
            "50th": 1087729,
            "90th": 1622802,
            "95th": 2656416,
            "99th": 3999250,
            "max": 4163708,
            "min": 700792
        },
        "bytes_in": {
            "total": 60600,
            "mean": 202
        },
        "bytes_out": {
            "total": 0,
            "mean": 0
        },
        "earliest": "2025-06-06T00:22:02.31337575+07:00",
        "latest": "2025-06-06T00:22:03.309721459+07:00",
        "end": "2025-06-06T00:22:03.310591042+07:00",
        "duration": 996345709,
        "wait": 869583,
        "requests": 300,
        "rate": 301.1003081461557,
        "throughput": 300.83774527597194,
        "success": 1,
        "status_codes": {
            "200": 300
        },
        "errors": []
    },
    {
        "latencies": {
            "total": 575360828,
            "mean": 1438402,
            "50th": 1009970,
            "90th": 1573750,
            "95th": 2895333,
            "99th": 14030041,
            "max": 21097667,
            "min": 667875
        },
        "bytes_in": {
            "total": 80801,
            "mean": 202.0025
        },
        "bytes_out": {
            "total": 0,
            "mean": 0
        },
        "earliest": "2025-06-06T00:22:03.313594625+07:00",
        "latest": "2025-06-06T00:22:04.310885541+07:00",
        "end": "2025-06-06T00:22:04.31185325+07:00",
        "duration": 997290916,
        "wait": 967709,
        "requests": 400,
        "rate": 401.08657722898585,
        "throughput": 400.6977650706499,
        "success": 1,
        "status_codes": {
            "200": 400
        },
        "errors": []
    },
    {
        "latencies": {
            "total": 492115948,
            "mean": 984231,
            "50th": 839166,
            "90th": 1140020,
            "95th": 2023069,
            "99th": 4285104,
            "max": 4776500,
            "min": 615333
        },
        "bytes_in": {
            "total": 101500,
            "mean": 203
        },
        "bytes_out": {
            "total": 0,
            "mean": 0
        },
        "earliest": "2025-06-06T00:22:04.314480875+07:00",
        "latest": "2025-06-06T00:22:05.31216925+07:00",
        "end": "2025-06-06T00:22:05.313075+07:00",
        "duration": 997688375,
        "wait": 905750,
        "requests": 500,
        "rate": 501.1584904955919,
        "throughput": 500.7039271335589,
        "success": 1,
        "status_codes": {
            "200": 500
        },
        "errors": []
    },
    {
        "latencies": {
            "total": 581096370,
            "mean": 968493,
            "50th": 842831,
            "90th": 1135027,
            "95th": 1529989,
            "99th": 4021041,
            "max": 5061125,
            "min": 625875
        },
        "bytes_in": {
            "total": 121800,
            "mean": 203
        },
        "bytes_out": {
            "total": 0,
            "mean": 0
        },
        "earliest": "2025-06-06T00:22:05.315151+07:00",
        "latest": "2025-06-06T00:22:06.313385583+07:00",
        "end": "2025-06-06T00:22:06.314058208+07:00",
        "duration": 998234583,
        "wait": 672625,
        "requests": 600,
        "rate": 601.061123525511,
        "throughput": 600.6563925004734,
        "success": 1,
        "status_codes": {
            "200": 600
        },
        "errors": []
    },
    {
        "latencies": {
            "total": 2454034902,
            "mean": 3505764,
            "50th": 867645,
            "90th": 1565029,
            "95th": 24468676,
            "99th": 57529687,
            "max": 64393375,
            "min": 627459
        },
        "bytes_in": {
            "total": 142100,
            "mean": 203
        },
        "bytes_out": {
            "total": 0,
            "mean": 0
        },
        "earliest": "2025-06-06T00:22:06.315806792+07:00",
        "latest": "2025-06-06T00:22:07.31425275+07:00",
        "end": "2025-06-06T00:22:07.315063333+07:00",
        "duration": 998445958,
        "wait": 810583,
        "requests": 700,
        "rate": 701.0895225638241,
        "throughput": 700.5208084997664,
        "success": 1,
        "status_codes": {
            "200": 700
        },
        "errors": []
    },
    {
        "latencies": {
            "total": 676380785,
            "mean": 845475,
            "50th": 768338,
            "90th": 976350,
            "95th": 1133714,
            "99th": 2713646,
            "max": 4549000,
            "min": 583042
        },
        "bytes_in": {
            "total": 162400,
            "mean": 203
        },
        "bytes_out": {
            "total": 0,
            "mean": 0
        },
        "earliest": "2025-06-06T00:22:07.316611875+07:00",
        "latest": "2025-06-06T00:22:08.31528525+07:00",
        "end": "2025-06-06T00:22:08.316071333+07:00",
        "duration": 998673375,
        "wait": 786083,
        "requests": 800,
        "rate": 801.0627098174116,
        "throughput": 800.4326674749423,
        "success": 1,
        "status_codes": {
            "200": 800
        },
        "errors": []
    },
    {
        "latencies": {
            "total": 879537822,
            "mean": 977264,
            "50th": 816987,
            "90th": 1056360,
            "95th": 1161245,
            "99th": 6896604,
            "max": 13256209,
            "min": 609042
        },
        "bytes_in": {
            "total": 182700,
            "mean": 203
        },
        "bytes_out": {
            "total": 0,
            "mean": 0
        },
        "earliest": "2025-06-06T00:22:08.317464584+07:00",
        "latest": "2025-06-06T00:22:09.316223584+07:00",
        "end": "2025-06-06T00:22:09.317163875+07:00",
        "duration": 998759000,
        "wait": 940291,
        "requests": 900,
        "rate": 901.1182877951538,
        "throughput": 900.2707195077925,
        "success": 1,
        "status_codes": {
            "200": 900
        },
        "errors": []
    },
    {
        "latencies": {
            "total": 1023706224,
            "mean": 1023706,
            "50th": 801118,
            "90th": 1056857,
            "95th": 1288926,
            "99th": 9574477,
            "max": 17576542,
            "min": 561875
        },
        "bytes_in": {
            "total": 203000,
            "mean": 203
        },
        "bytes_out": {
            "total": 0,
            "mean": 0
        },
        "earliest": "2025-06-06T00:22:09.31840875+07:00",
        "latest": "2025-06-06T00:22:10.317331541+07:00",
        "end": "2025-06-06T00:22:10.323179125+07:00",
        "duration": 998922791,
        "wait": 5847584,
        "requests": 1000,
        "rate": 1001.0783706305485,
        "throughput": 995.2522734361071,
        "success": 1,
        "status_codes": {
            "200": 1000
        },
        "errors": []
    },
    {
        "latencies": {
            "total": 915035461,
            "mean": 831850,
            "50th": 731643,
            "90th": 995279,
            "95th": 1403431,
            "99th": 3110659,
            "max": 5461750,
            "min": 540041
        },
        "bytes_in": {
            "total": 223300,
            "mean": 203
        },
        "bytes_out": {
            "total": 0,
            "mean": 0
        },
        "earliest": "2025-06-06T00:22:10.324371792+07:00",
        "latest": "2025-06-06T00:22:11.323300709+07:00",
        "end": "2025-06-06T00:22:11.323882334+07:00",
        "duration": 998928917,
        "wait": 581625,
        "requests": 1100,
        "rate": 1101.1794545937646,
        "throughput": 1100.5386674550953,
        "success": 1,
        "status_codes": {
            "200": 1100
        },
        "errors": []
    },
    {
        "latencies": {
            "total": 976540280,
            "mean": 813783,
            "50th": 718752,
            "90th": 943964,
            "95th": 1174443,
            "99th": 3311873,
            "max": 4629209,
            "min": 511208
        },
        "bytes_in": {
            "total": 243600,
            "mean": 203
        },
        "bytes_out": {
            "total": 0,
            "mean": 0
        },
        "earliest": "2025-06-06T00:22:11.324924583+07:00",
        "latest": "2025-06-06T00:22:12.326631667+07:00",
        "end": "2025-06-06T00:22:12.327424833+07:00",
        "duration": 1001707084,
        "wait": 793166,
        "requests": 1200,
        "rate": 1197.9549902035035,
        "throughput": 1197.0071827912263,
        "success": 1,
        "status_codes": {
            "200": 1200
        },
        "errors": []
    },
    {
        "latencies": {
            "total": 1082866108,
            "mean": 833615,
            "50th": 736391,
            "90th": 1021103,
            "95th": 1293075,
            "99th": 2840458,
            "max": 5547375,
            "min": 529917
        },
        "bytes_in": {
            "total": 263697,
            "mean": 203
        },
        "bytes_out": {
            "total": 0,
            "mean": 0
        },
        "earliest": "2025-06-06T00:22:12.32848075+07:00",
        "latest": "2025-06-06T00:22:13.327674209+07:00",
        "end": "2025-06-06T00:22:13.3283965+07:00",
        "duration": 999193459,
        "wait": 722291,
        "requests": 1299,
        "rate": 1300.0485424514773,
        "throughput": 1299.10944997116,
        "success": 1,
        "status_codes": {
            "200": 1299
        },
        "errors": []
    },
    {
        "latencies": {
            "total": 1181191919,
            "mean": 843708,
            "50th": 758726,
            "90th": 1037518,
            "95th": 1321754,
            "99th": 2478013,
            "max": 5181542,
            "min": 563750
        },
        "bytes_in": {
            "total": 284700,
            "mean": 203.35714285714286
        },
        "bytes_out": {
            "total": 0,
            "mean": 0
        },
        "earliest": "2025-06-06T00:22:13.329407917+07:00",
        "latest": "2025-06-06T00:22:14.328749042+07:00",
        "end": "2025-06-06T00:22:14.3294805+07:00",
        "duration": 999341125,
        "wait": 731458,
        "requests": 1400,
        "rate": 1400.9230331634756,
        "throughput": 1399.8983911750736,
        "success": 1,
        "status_codes": {
            "200": 1400
        },
        "errors": []
    },
    {
        "latencies": {
            "total": 1316065368,
            "mean": 877376,
            "50th": 794596,
            "90th": 1071646,
            "95th": 1345315,
            "99th": 2551854,
            "max": 3630458,
            "min": 547917
        },
        "bytes_in": {
            "total": 306000,
            "mean": 204
        },
        "bytes_out": {
            "total": 0,
            "mean": 0
        },
        "earliest": "2025-06-06T00:22:14.330452833+07:00",
        "latest": "2025-06-06T00:22:15.329702916+07:00",
        "end": "2025-06-06T00:22:15.33030375+07:00",
        "duration": 999250083,
        "wait": 600834,
        "requests": 1500,
        "rate": 1501.1257196963377,
        "throughput": 1500.2236578435823,
        "success": 1,
        "status_codes": {
            "200": 1500
        },
        "errors": []
    },
    {
        "latencies": {
            "total": 1445102577,
            "mean": 903189,
            "50th": 807570,
            "90th": 1094656,
            "95th": 1479042,
            "99th": 3087564,
            "max": 4518416,
            "min": 521459
        },
        "bytes_in": {
            "total": 326400,
            "mean": 204
        },
        "bytes_out": {
            "total": 0,
            "mean": 0
        },
        "earliest": "2025-06-06T00:22:15.331114875+07:00",
        "latest": "2025-06-06T00:22:16.330476208+07:00",
        "end": "2025-06-06T00:22:16.331185833+07:00",
        "duration": 999361333,
        "wait": 709625,
        "requests": 1600,
        "rate": 1601.0225202499405,
        "throughput": 1599.886475255489,
        "success": 1,
        "status_codes": {
            "200": 1600
        },
        "errors": []
    },
    {
        "latencies": {
            "total": 1431137124,
            "mean": 841845,
            "50th": 788552,
            "90th": 985642,
            "95th": 1161355,
            "99th": 2205943,
            "max": 3155792,
            "min": 554083
        },
        "bytes_in": {
            "total": 346800,
            "mean": 204
        },
        "bytes_out": {
            "total": 0,
            "mean": 0
        },
        "earliest": "2025-06-06T00:22:16.332000166+07:00",
        "latest": "2025-06-06T00:22:17.331338333+07:00",
        "end": "2025-06-06T00:22:17.331988291+07:00",
        "duration": 999338167,
        "wait": 649958,
        "requests": 1700,
        "rate": 1701.125861232117,
        "throughput": 1700.0201877397294,
        "success": 1,
        "status_codes": {
            "200": 1700
        },
        "errors": []
    },
    {
        "latencies": {
            "total": 1484658610,
            "mean": 824810,
            "50th": 787532,
            "90th": 956092,
            "95th": 1081627,
            "99th": 1822217,
            "max": 2728375,
            "min": 553041
        },
        "bytes_in": {
            "total": 367200,
            "mean": 204
        },
        "bytes_out": {
            "total": 0,
            "mean": 0
        },
        "earliest": "2025-06-06T00:22:17.332701417+07:00",
        "latest": "2025-06-06T00:22:18.332154875+07:00",
        "end": "2025-06-06T00:22:18.33287775+07:00",
        "duration": 999453458,
        "wait": 722875,
        "requests": 1800,
        "rate": 1800.9843135687065,
        "throughput": 1799.6826565581212,
        "success": 1,
        "status_codes": {
            "200": 1800
        },
        "errors": []
    },
    {
        "latencies": {
            "total": 2578459009,
            "mean": 1357083,
            "50th": 807863,
            "90th": 1259126,
            "95th": 3170698,
            "99th": 16168240,
            "max": 23650000,
            "min": 518791
        },
        "bytes_in": {
            "total": 387600,
            "mean": 204
        },
        "bytes_out": {
            "total": 0,
            "mean": 0
        },
        "earliest": "2025-06-06T00:22:18.333590667+07:00",
        "latest": "2025-06-06T00:22:19.333020792+07:00",
        "end": "2025-06-06T00:22:19.334012958+07:00",
        "duration": 999430125,
        "wait": 992166,
        "requests": 1900,
        "rate": 1901.0833798911156,
        "throughput": 1899.1979857833855,
        "success": 1,
        "status_codes": {
            "200": 1900
        },
        "errors": []
    },
    {
        "latencies": {
            "total": 1663832290,
            "mean": 831916,
            "50th": 791142,
            "90th": 982022,
            "95th": 1121907,
            "99th": 2002259,
            "max": 3111458,
            "min": 491208
        },
        "bytes_in": {
            "total": 408000,
            "mean": 204
        },
        "bytes_out": {
            "total": 0,
            "mean": 0
        },
        "earliest": "2025-06-06T00:22:19.334707167+07:00",
        "latest": "2025-06-06T00:22:20.334198667+07:00",
        "end": "2025-06-06T00:22:20.334883542+07:00",
        "duration": 999491500,
        "wait": 684875,
        "requests": 2000,
        "rate": 2001.0175174076019,
        "throughput": 1999.64731220531,
        "success": 1,
        "status_codes": {
            "200": 2000
        },
        "errors": []
    },
    {
        "latencies": {
            "total": 1791609147,
            "mean": 853147,
            "50th": 807928,
            "90th": 1021219,
            "95th": 1155254,
            "99th": 2016237,
            "max": 3010416,
            "min": 534375
        },
        "bytes_in": {
            "total": 428400,
            "mean": 204
        },
        "bytes_out": {
            "total": 0,
            "mean": 0
        },
        "earliest": "2025-06-06T00:22:20.335527958+07:00",
        "latest": "2025-06-06T00:22:21.335015375+07:00",
        "end": "2025-06-06T00:22:21.335674208+07:00",
        "duration": 999487417,
        "wait": 658833,
        "requests": 2100,
        "rate": 2101.0769763397634,
        "throughput": 2099.692919910463,
        "success": 1,
        "status_codes": {
            "200": 2100
        },
        "errors": []
    },
    {
        "latencies": {
            "total": 1901798596,
            "mean": 864453,
            "50th": 804351,
            "90th": 1031700,
            "95th": 1248216,
            "99th": 2287543,
            "max": 4540459,
            "min": 509375
        },
        "bytes_in": {
            "total": 448800,
            "mean": 204
        },
        "bytes_out": {
            "total": 0,
            "mean": 0
        },
        "earliest": "2025-06-06T00:22:21.336318166+07:00",
        "latest": "2025-06-06T00:22:22.335790708+07:00",
        "end": "2025-06-06T00:22:22.336561041+07:00",
        "duration": 999472542,
        "wait": 770333,
        "requests": 2200,
        "rate": 2201.1610199892816,
        "throughput": 2199.465804742673,
        "success": 1,
        "status_codes": {
            "200": 2200
        },
        "errors": []
    },
    {
        "latencies": {
            "total": 1992430360,
            "mean": 866274,
            "50th": 814229,
            "90th": 1045669,
            "95th": 1184841,
            "99th": 2131543,
            "max": 3924625,
            "min": 544125
        },
        "bytes_in": {
            "total": 469200,
            "mean": 204
        },
        "bytes_out": {
            "total": 0,
            "mean": 0
        },
        "earliest": "2025-06-06T00:22:22.337182417+07:00",
        "latest": "2025-06-06T00:22:23.336713+07:00",
        "end": "2025-06-06T00:22:23.337505792+07:00",
        "duration": 999530583,
        "wait": 792792,
        "requests": 2300,
        "rate": 2301.080166148353,
        "throughput": 2299.2564779364475,
        "success": 1,
        "status_codes": {
            "200": 2300
        },
        "errors": []
    },
    {
        "latencies": {
            "total": 2400696071,
            "mean": 1000290,
            "50th": 854738,
            "90th": 1146094,
            "95th": 1510568,
            "99th": 4962031,
            "max": 11879875,
            "min": 518625
        },
        "bytes_in": {
            "total": 489600,
            "mean": 204
        },
        "bytes_out": {
            "total": 0,
            "mean": 0
        },
        "earliest": "2025-06-06T00:22:23.338194792+07:00",
        "latest": "2025-06-06T00:22:24.337770625+07:00",
        "end": "2025-06-06T00:22:24.338437792+07:00",
        "duration": 999575833,
        "wait": 667167,
        "requests": 2400,
        "rate": 2401.0184327855795,
        "throughput": 2399.416941683171,
        "success": 1,
        "status_codes": {
            "200": 2400
        },
        "errors": []
    },
    {
        "latencies": {
            "total": 2347510769,
            "mean": 939004,
            "50th": 859692,
            "90th": 1180704,
            "95th": 1406380,
            "99th": 2589455,
            "max": 4484458,
            "min": 576125
        },
        "bytes_in": {
            "total": 510000,
            "mean": 204
        },
        "bytes_out": {
            "total": 0,
            "mean": 0
        },
        "earliest": "2025-06-06T00:22:24.339015958+07:00",
        "latest": "2025-06-06T00:22:25.338621958+07:00",
        "end": "2025-06-06T00:22:25.339283667+07:00",
        "duration": 999606000,
        "wait": 661709,
        "requests": 2500,
        "rate": 2500.985388242968,
        "throughput": 2499.3309066223187,
        "success": 1,
        "status_codes": {
            "200": 2500
        },
        "errors": []
    },
    {
        "latencies": {
            "total": 2509362946,
            "mean": 965139,
            "50th": 834921,
            "90th": 1167325,
            "95th": 1533933,
            "99th": 3885460,
            "max": 9399666,
            "min": 526917
        },
        "bytes_in": {
            "total": 530400,
            "mean": 204
        },
        "bytes_out": {
            "total": 0,
            "mean": 0
        },
        "earliest": "2025-06-06T00:22:25.339788875+07:00",
        "latest": "2025-06-06T00:22:26.339402583+07:00",
        "end": "2025-06-06T00:22:26.340421625+07:00",
        "duration": 999613708,
        "wait": 1019042,
        "requests": 2600,
        "rate": 2601.0047473258537,
        "throughput": 2598.355890310406,
        "success": 1,
        "status_codes": {
            "200": 2600
        },
        "errors": []
    },
    {
        "latencies": {
            "total": 2603250588,
            "mean": 964166,
            "50th": 884668,
            "90th": 1236695,
            "95th": 1489484,
            "99th": 2436976,
            "max": 4725000,
            "min": 557500
        },
        "bytes_in": {
            "total": 550800,
            "mean": 204
        },
        "bytes_out": {
            "total": 0,
            "mean": 0
        },
        "earliest": "2025-06-06T00:22:26.340922083+07:00",
        "latest": "2025-06-06T00:22:27.340575083+07:00",
        "end": "2025-06-06T00:22:27.341385166+07:00",
        "duration": 999653000,
        "wait": 810083,
        "requests": 2700,
        "rate": 2700.93722521715,
        "throughput": 2698.7502546358323,
        "success": 1,
        "status_codes": {
            "200": 2700
        },
        "errors": []
    },
    {
        "latencies": {
            "total": 3614213635,
            "mean": 1290790,
            "50th": 854925,
            "90th": 1165561,
            "95th": 1655977,
            "99th": 17927402,
            "max": 27585541,
            "min": 535125
        },
        "bytes_in": {
            "total": 571200,
            "mean": 204
        },
        "bytes_out": {
            "total": 0,
            "mean": 0
        },
        "earliest": "2025-06-06T00:22:27.341890792+07:00",
        "latest": "2025-06-06T00:22:28.341551417+07:00",
        "end": "2025-06-06T00:22:28.342462417+07:00",
        "duration": 999660625,
        "wait": 911000,
        "requests": 2800,
        "rate": 2800.9505726005764,
        "throughput": 2798.4003643917044,
        "success": 1,
        "status_codes": {
            "200": 2800
        },
        "errors": []
    },
    {
        "latencies": {
            "total": 2686111392,
            "mean": 926245,
            "50th": 856897,
            "90th": 1148477,
            "95th": 1389011,
            "99th": 2366095,
            "max": 4583583,
            "min": 519166
        },
        "bytes_in": {
            "total": 591600,
            "mean": 204
        },
        "bytes_out": {
            "total": 0,
            "mean": 0
        },
        "earliest": "2025-06-06T00:22:28.342967584+07:00",
        "latest": "2025-06-06T00:22:29.342611334+07:00",
        "end": "2025-06-06T00:22:29.343483959+07:00",
        "duration": 999643750,
        "wait": 872625,
        "requests": 2900,
        "rate": 2901.0334931819457,
        "throughput": 2898.5032853660196,
        "success": 1,
        "status_codes": {
            "200": 2900
        },
        "errors": []
    },
    {
        "latencies": {
            "total": 2880468289,
            "mean": 960156,
            "50th": 887401,
            "90th": 1200541,
            "95th": 1389641,
            "99th": 2633161,
            "max": 4680292,
            "min": 542208
        },
        "bytes_in": {
            "total": 612000,
            "mean": 204
        },
        "bytes_out": {
            "total": 0,
            "mean": 0
        },
        "earliest": "2025-06-06T00:22:29.344025167+07:00",
        "latest": "2025-06-06T00:22:30.343608667+07:00",
        "end": "2025-06-06T00:22:30.344456334+07:00",
        "duration": 999583500,
        "wait": 847667,
        "requests": 3000,
        "rate": 3001.250020633594,
        "throughput": 2998.7070564745813,
        "success": 1,
        "status_codes": {
            "200": 3000
        },
        "errors": []
    },
    {
        "latencies": {
            "total": 18207510368,
            "mean": 5907693,
            "50th": 941153,
            "90th": 1459036,
            "95th": 3038701,
            "99th": 137447671,
            "max": 269839458,
            "min": 568167
        },
        "bytes_in": {
            "total": 628728,
            "mean": 204
        },
        "bytes_out": {
            "total": 0,
            "mean": 0
        },
        "earliest": "2025-06-06T00:22:30.344935292+07:00",
        "latest": "2025-06-06T00:22:31.343947833+07:00",
        "end": "2025-06-06T00:22:31.608463875+07:00",
        "duration": 999012541,
        "wait": 264516042,
        "requests": 3082,
        "rate": 3085.04635679043,
        "throughput": 2439.2008550233168,
        "success": 1,
        "status_codes": {
            "200": 3082
        },
        "errors": []
    },
    {
        "latencies": {
            "total": 24083433083,
            "mean": 7526072,
            "50th": 1010269,
            "90th": 24802147,
            "95th": 45163628,
            "99th": 67029451,
            "max": 304809459,
            "min": 520917
        },
        "bytes_in": {
            "total": 652800,
            "mean": 204
        },
        "bytes_out": {
            "total": 0,
            "mean": 0
        },
        "earliest": "2025-06-06T00:22:31.609199042+07:00",
        "latest": "2025-06-06T00:22:32.608869583+07:00",
        "end": "2025-06-06T00:22:32.609897792+07:00",
        "duration": 999670541,
        "wait": 1028209,
        "requests": 3200,
        "rate": 3201.0546162528162,
        "throughput": 3197.765561314032,
        "success": 1,
        "status_codes": {
            "200": 3200
        },
        "errors": []
    },
    {
        "latencies": {
            "total": 3325498663,
            "mean": 1007726,
            "50th": 910923,
            "90th": 1271132,
            "95th": 1576112,
            "99th": 2939420,
            "max": 6494042,
            "min": 545125
        },
        "bytes_in": {
            "total": 673200,
            "mean": 204
        },
        "bytes_out": {
            "total": 0,
            "mean": 0
        },
        "earliest": "2025-06-06T00:22:32.610413209+07:00",
        "latest": "2025-06-06T00:22:33.610131834+07:00",
        "end": "2025-06-06T00:22:33.610987709+07:00",
        "duration": 999718625,
        "wait": 855875,
        "requests": 3300,
        "rate": 3300.928798840774,
        "throughput": 3298.1052385404587,
        "success": 1,
        "status_codes": {
            "200": 3300
        },
        "errors": []
    },
    {
        "latencies": {
            "total": 6260665558,
            "mean": 1841372,
            "50th": 931682,
            "90th": 2329534,
            "95th": 5956860,
            "99th": 24586354,
            "max": 38444625,
            "min": 541875
        },
        "bytes_in": {
            "total": 693600,
            "mean": 204
        },
        "bytes_out": {
            "total": 0,
            "mean": 0
        },
        "earliest": "2025-06-06T00:22:33.611457375+07:00",
        "latest": "2025-06-06T00:22:34.611107959+07:00",
        "end": "2025-06-06T00:22:34.611874125+07:00",
        "duration": 999650584,
        "wait": 766166,
        "requests": 3400,
        "rate": 3401.188429656337,
        "throughput": 3398.583640267918,
        "success": 1,
        "status_codes": {
            "200": 3400
        },
        "errors": []
    },
    {
        "latencies": {
            "total": 3802539326,
            "mean": 1086439,
            "50th": 938215,
            "90th": 1410697,
            "95th": 1843209,
            "99th": 4120309,
            "max": 7486334,
            "min": 536708
        },
        "bytes_in": {
            "total": 714000,
            "mean": 204
        },
        "bytes_out": {
            "total": 0,
            "mean": 0
        },
        "earliest": "2025-06-06T00:22:34.612307458+07:00",
        "latest": "2025-06-06T00:22:35.6119705+07:00",
        "end": "2025-06-06T00:22:35.612913458+07:00",
        "duration": 999663042,
        "wait": 942958,
        "requests": 3500,
        "rate": 3501.179750526378,
        "throughput": 3497.880284547564,
        "success": 1,
        "status_codes": {
            "200": 3500
        },
        "errors": []
    },
    {
        "latencies": {
            "total": 4266661952,
            "mean": 1185183,
            "50th": 971465,
            "90th": 1708671,
            "95th": 2744861,
            "99th": 4900415,
            "max": 7559750,
            "min": 479250
        },
        "bytes_in": {
            "total": 734400,
            "mean": 204
        },
        "bytes_out": {
            "total": 0,
            "mean": 0
        },
        "earliest": "2025-06-06T00:22:35.613328792+07:00",
        "latest": "2025-06-06T00:22:36.613050625+07:00",
        "end": "2025-06-06T00:22:36.616324583+07:00",
        "duration": 999721833,
        "wait": 3273958,
        "requests": 3600,
        "rate": 3601.0016798342745,
        "throughput": 3589.2473650470183,
        "success": 1,
        "status_codes": {
            "200": 3600
        },
        "errors": []
    },
    {
        "latencies": {
            "total": 5185991287,
            "mean": 1401619,
            "50th": 958617,
            "90th": 1544883,
            "95th": 2730399,
            "99th": 15991259,
            "max": 22601292,
            "min": 514667
        },
        "bytes_in": {
            "total": 754800,
            "mean": 204
        },
        "bytes_out": {
            "total": 0,
            "mean": 0
        },
        "earliest": "2025-06-06T00:22:36.616743125+07:00",
        "latest": "2025-06-06T00:22:37.616471875+07:00",
        "end": "2025-06-06T00:22:37.617431208+07:00",
        "duration": 999728750,
        "wait": 959333,
        "requests": 3700,
        "rate": 3701.003897307144,
        "throughput": 3697.455843490843,
        "success": 1,
        "status_codes": {
            "200": 3700
        },
        "errors": []
    },
    {
        "latencies": {
            "total": 3893536113,
            "mean": 1024614,
            "50th": 929417,
            "90th": 1299840,
            "95th": 1597191,
            "99th": 3151156,
            "max": 6196875,
            "min": 478750
        },
        "bytes_in": {
            "total": 775200,
            "mean": 204
        },
        "bytes_out": {
            "total": 0,
            "mean": 0
        },
        "earliest": "2025-06-06T00:22:37.617847541+07:00",
        "latest": "2025-06-06T00:22:38.617542+07:00",
        "end": "2025-06-06T00:22:38.621702416+07:00",
        "duration": 999694459,
        "wait": 4160416,
        "requests": 3800,
        "rate": 3801.161410658574,
        "throughput": 3785.4077263907293,
        "success": 1,
        "status_codes": {
            "200": 3800
        },
        "errors": []
    },
    {
        "latencies": {
            "total": 4534080182,
            "mean": 1162584,
            "50th": 931046,
            "90th": 1360629,
            "95th": 1794740,
            "99th": 8445050,
            "max": 19464584,
            "min": 471625
        },
        "bytes_in": {
            "total": 795600,
            "mean": 204
        },
        "bytes_out": {
            "total": 0,
            "mean": 0
        },
        "earliest": "2025-06-06T00:22:38.622134541+07:00",
        "latest": "2025-06-06T00:22:39.621873625+07:00",
        "end": "2025-06-06T00:22:39.634555791+07:00",
        "duration": 999739084,
        "wait": 12682166,
        "requests": 3900,
        "rate": 3901.017837970212,
        "throughput": 3852.1514636323564,
        "success": 1,
        "status_codes": {
            "200": 3900
        },
        "errors": []
    },
    {
        "latencies": {
            "total": 4380074933,
            "mean": 1095018,
            "50th": 958640,
            "90th": 1463500,
            "95th": 2011054,
            "99th": 3616528,
            "max": 7150291,
            "min": 478042
        },
        "bytes_in": {
            "total": 816000,
            "mean": 204
        },
        "bytes_out": {
            "total": 0,
            "mean": 0
        },
        "earliest": "2025-06-06T00:22:39.634963416+07:00",
        "latest": "2025-06-06T00:22:40.634729708+07:00",
        "end": "2025-06-06T00:22:40.635936375+07:00",
        "duration": 999766292,
        "wait": 1206667,
        "requests": 4000,
        "rate": 4000.935050528789,
        "throughput": 3996.11194691624,
        "success": 1,
        "status_codes": {
            "200": 4000
        },
        "errors": []
    },
    {
        "latencies": {
            "total": 5459167598,
            "mean": 1331504,
            "50th": 998962,
            "90th": 1959384,
            "95th": 2917751,
            "99th": 9036995,
            "max": 16461584,
            "min": 455958
        },
        "bytes_in": {
            "total": 836400,
            "mean": 204
        },
        "bytes_out": {
            "total": 0,
            "mean": 0
        },
        "earliest": "2025-06-06T00:22:40.636362125+07:00",
        "latest": "2025-06-06T00:22:41.636125292+07:00",
        "end": "2025-06-06T00:22:41.636997958+07:00",
        "duration": 999763167,
        "wait": 872666,
        "requests": 4100,
        "rate": 4100.971245322943,
        "throughput": 4097.394741209512,
        "success": 1,
        "status_codes": {
            "200": 4100
        },
        "errors": []
    },
    {
        "latencies": {
            "total": 7802792214,
            "mean": 1857807,
            "50th": 1009691,
            "90th": 2260913,
            "95th": 5511457,
            "99th": 24188134,
            "max": 32019000,
            "min": 521416
        },
        "bytes_in": {
            "total": 856800,
            "mean": 204
        },
        "bytes_out": {
            "total": 0,
            "mean": 0
        },
        "earliest": "2025-06-06T00:22:41.637372625+07:00",
        "latest": "2025-06-06T00:22:42.637129792+07:00",
        "end": "2025-06-06T00:22:42.638048042+07:00",
        "duration": 999757167,
        "wait": 918250,
        "requests": 4200,
        "rate": 4201.020146325192,
        "throughput": 4197.1651632969015,
        "success": 1,
        "status_codes": {
            "200": 4200
        },
        "errors": []
    },
    {
        "latencies": {
            "total": 9880648323,
            "mean": 2297825,
            "50th": 1011672,
            "90th": 2243847,
            "95th": 7810937,
            "99th": 34863360,
            "max": 46973792,
            "min": 501750
        },
        "bytes_in": {
            "total": 877200,
            "mean": 204
        },
        "bytes_out": {
            "total": 0,
            "mean": 0
        },
        "earliest": "2025-06-06T00:22:42.638402375+07:00",
        "latest": "2025-06-06T00:22:43.638198166+07:00",
        "end": "2025-06-06T00:22:43.639221166+07:00",
        "duration": 999795791,
        "wait": 1023000,
        "requests": 4300,
        "rate": 4300.878278052282,
        "throughput": 4296.482079141938,
        "success": 1,
        "status_codes": {
            "200": 4300
        },
        "errors": []
    },
    {
        "latencies": {
            "total": 5417218491,
            "mean": 1231186,
            "50th": 1002049,
            "90th": 1696290,
            "95th": 2634528,
            "99th": 5765193,
            "max": 8744792,
            "min": 492083
        },
        "bytes_in": {
            "total": 897600,
            "mean": 204
        },
        "bytes_out": {
            "total": 0,
            "mean": 0
        },
        "earliest": "2025-06-06T00:22:43.639576792+07:00",
        "latest": "2025-06-06T00:22:44.639317625+07:00",
        "end": "2025-06-06T00:22:44.6401485+07:00",
        "duration": 999740833,
        "wait": 830875,
        "requests": 4400,
        "rate": 4401.140630413763,
        "throughput": 4397.485922118437,
        "success": 1,
        "status_codes": {
            "200": 4400
        },
        "errors": []
    },
    {
        "latencies": {
            "total": 5233979351,
            "mean": 1163106,
            "50th": 992614,
            "90th": 1557718,
            "95th": 2174650,
            "99th": 4590514,
            "max": 10014417,
            "min": 458750
        },
        "bytes_in": {
            "total": 921479,
            "mean": 204.77311111111112
        },
        "bytes_out": {
            "total": 0,
            "mean": 0
        },
        "earliest": "2025-06-06T00:22:44.640528083+07:00",
        "latest": "2025-06-06T00:22:45.640295708+07:00",
        "end": "2025-06-06T00:22:45.641043167+07:00",
        "duration": 999767625,
        "wait": 747459,
        "requests": 4500,
        "rate": 4501.045930548111,
        "throughput": 4497.683315287228,
        "success": 1,
        "status_codes": {
            "200": 4500
        },
        "errors": []
    },
    {
        "latencies": {
            "total": 10556810354,
            "mean": 2294958,
            "50th": 1185239,
            "90th": 3614349,
            "95th": 6786621,
            "99th": 26277348,
            "max": 39546292,
            "min": 476125
        },
        "bytes_in": {
            "total": 943000,
            "mean": 205
        },
        "bytes_out": {
            "total": 0,
            "mean": 0
        },
        "earliest": "2025-06-06T00:22:45.641415875+07:00",
        "latest": "2025-06-06T00:22:46.641224542+07:00",
        "end": "2025-06-06T00:22:46.645426+07:00",
        "duration": 999808667,
        "wait": 4201458,
        "requests": 4600,
        "rate": 4600.880300230484,
        "throughput": 4581.627102615125,
        "success": 1,
        "status_codes": {
            "200": 4600
        },
        "errors": []
    },
    {
        "latencies": {
            "total": 5867476618,
            "mean": 1248399,
            "50th": 1041481,
            "90th": 1801025,
            "95th": 2568330,
            "99th": 4741817,
            "max": 11823834,
            "min": 416541
        },
        "bytes_in": {
            "total": 963500,
            "mean": 205
        },
        "bytes_out": {
            "total": 0,
            "mean": 0
        },
        "earliest": "2025-06-06T00:22:46.645801166+07:00",
        "latest": "2025-06-06T00:22:47.645560583+07:00",
        "end": "2025-06-06T00:22:47.647250541+07:00",
        "duration": 999759417,
        "wait": 1689958,
        "requests": 4700,
        "rate": 4701.131012202309,
        "throughput": 4693.197796443779,
        "success": 1,
        "status_codes": {
            "200": 4700
        },
        "errors": []
    },
    {
        "latencies": {
            "total": 5457447080,
            "mean": 1136968,
            "50th": 984610,
            "90th": 1485011,
            "95th": 2022687,
            "99th": 4120331,
            "max": 9594458,
            "min": 540292
        },
        "bytes_in": {
            "total": 984000,
            "mean": 205
        },
        "bytes_out": {
            "total": 0,
            "mean": 0
        },
        "earliest": "2025-06-06T00:22:47.647618459+07:00",
        "latest": "2025-06-06T00:22:48.647420542+07:00",
        "end": "2025-06-06T00:22:48.648643042+07:00",
        "duration": 999802083,
        "wait": 1222500,
        "requests": 4800,
        "rate": 4800.950189658687,
        "throughput": 4795.0870353400705,
        "success": 1,
        "status_codes": {
            "200": 4800
        },
        "errors": []
    },
    {
        "latencies": {
            "total": 6178545956,
            "mean": 1260927,
            "50th": 1066854,
            "90th": 1757557,
            "95th": 2378812,
            "99th": 4991053,
            "max": 9554458,
            "min": 468500
        },
        "bytes_in": {
            "total": 1004500,
            "mean": 205
        },
        "bytes_out": {
            "total": 0,
            "mean": 0
        },
        "earliest": "2025-06-06T00:22:48.649018208+07:00",
        "latest": "2025-06-06T00:22:49.648826792+07:00",
        "end": "2025-06-06T00:22:49.649675375+07:00",
        "duration": 999808584,
        "wait": 848583,
        "requests": 4900,
        "rate": 4900.93811797079,
        "throughput": 4896.781996465729,
        "success": 1,
        "status_codes": {
            "200": 4900
        },
        "errors": []
    },
    {
        "latencies": {
            "total": 7459711760,
            "mean": 1491942,
            "50th": 1086411,
            "90th": 2039636,
            "95th": 3247572,
            "99th": 11997642,
            "max": 22285708,
            "min": 522375
        },
        "bytes_in": {
            "total": 1025000,
            "mean": 205
        },
        "bytes_out": {
            "total": 0,
            "mean": 0
        },
        "earliest": "2025-06-06T00:22:49.650033458+07:00",
        "latest": "2025-06-06T00:22:50.649785833+07:00",
        "end": "2025-06-06T00:22:50.650736375+07:00",
        "duration": 999752375,
        "wait": 950542,
        "requests": 5000,
        "rate": 5001.238431666641,
        "throughput": 4996.487883726235,
        "success": 1,
        "status_codes": {
            "200": 5000
        },
        "errors": []
    }
]