[
    {
        "latencies": {
            "total": 301873035,
            "mean": 3018730,
            "50th": 2838854,
            "90th": 4471146,
            "95th": 5339895,
            "99th": 7630958,
            "max": 8813167,
            "min": 1002208
        },
        "bytes_in": {
            "total": 17392,
            "mean": 173.92
        },
        "bytes_out": {
            "total": 17392,
            "mean": 173.92
        },
        "earliest": "2025-06-08T23:08:17.912913458+07:00",
        "latest": "2025-06-08T23:08:18.902511708+07:00",
        "end": "2025-06-08T23:08:18.906169625+07:00",
        "duration": 989598250,
        "wait": 3657917,
        "requests": 100,
        "rate": 101.05110836645073,
        "throughput": 100.67896210706337,
        "success": 1,
        "status_codes": {
            "200": 100
        },
        "errors": []
    },
    {
        "latencies": {
            "total": 305779286,
            "mean": 1528896,
            "50th": 1404909,
            "90th": 2049666,
            "95th": 2857436,
            "99th": 4087104,
            "max": 5590875,
            "min": 771708
        },
        "bytes_in": {
            "total": 35000,
            "mean": 175
        },
        "bytes_out": {
            "total": 35000,
            "mean": 175
        },
        "earliest": "2025-06-08T23:08:18.911965875+07:00",
        "latest": "2025-06-08T23:08:19.906705+07:00",
        "end": "2025-06-08T23:08:19.908245042+07:00",
        "duration": 994739125,
        "wait": 1540042,
        "requests": 200,
        "rate": 201.0577396360076,
        "throughput": 200.74694586080813,
        "success": 1,
        "status_codes": {
            "200": 200
        },
        "errors": []
    },
    {
        "latencies": {
            "total": 402599876,
            "mean": 1341999,
            "50th": 1241458,
            "90th": 1622135,
            "95th": 1900499,
            "99th": 4617103,
            "max": 9149083,
            "min": 713084
        },
        "bytes_in": {
            "total": 52500,
            "mean": 175
        },
        "bytes_out": {
            "total": 52500,
            "mean": 175
        },
        "earliest": "2025-06-08T23:08:19.911945042+07:00",
        "latest": "2025-06-08T23:08:20.908744333+07:00",
        "end": "2025-06-08T23:08:20.910487542+07:00",
        "duration": 996799291,
        "wait": 1743209,
        "requests": 300,
        "rate": 300.96329592995266,
        "throughput": 300.4378882220837,
        "success": 1,
        "status_codes": {
            "200": 300
        },
        "errors": []
    },
    {
        "latencies": {
            "total": 463501497,
            "mean": 1158753,
            "50th": 1068621,
            "90th": 1433222,
            "95th": 1838353,
            "99th": 2996332,
            "max": 4604750,
            "min": 648375
        },
        "bytes_in": {
            "total": 70001,
            "mean": 175.0025
        },
        "bytes_out": {
            "total": 70001,
            "mean": 175.0025
        },
        "earliest": "2025-06-08T23:08:20.913464584+07:00",
        "latest": "2025-06-08T23:08:21.910876959+07:00",
        "end": "2025-06-08T23:08:21.911659292+07:00",
        "duration": 997412375,
        "wait": 782333,
        "requests": 400,
        "rate": 401.0377352697273,
        "throughput": 400.7234227893743,
        "success": 1,
        "status_codes": {
            "200": 400
        },
        "errors": []
    },
    {
        "latencies": {
            "total": 527950918,
            "mean": 1055901,
            "50th": 978164,
            "90th": 1272458,
            "95th": 1554967,
            "99th": 3606186,
            "max": 6847208,
            "min": 618583
        },
        "bytes_in": {
            "total": 88000,
            "mean": 176
        },
        "bytes_out": {
            "total": 88000,
            "mean": 176
        },
        "earliest": "2025-06-08T23:08:21.914023458+07:00",
        "latest": "2025-06-08T23:08:22.911896792+07:00",
        "end": "2025-06-08T23:08:22.912865417+07:00",
        "duration": 997873334,
        "wait": 968625,
        "requests": 500,
        "rate": 501.06559917353195,
        "throughput": 500.57969180687974,
        "success": 1,
        "status_codes": {
            "200": 500
        },
        "errors": []
    },
    {
        "latencies": {
            "total": 616873178,
            "mean": 1028121,
            "50th": 856945,
            "90th": 1218668,
            "95th": 1576579,
            "99th": 5655187,
            "max": 10706000,
            "min": 589083
        },
        "bytes_in": {
            "total": 105600,
            "mean": 176
        },
        "bytes_out": {
            "total": 105600,
            "mean": 176
        },
        "earliest": "2025-06-08T23:08:22.914852209+07:00",
        "latest": "2025-06-08T23:08:23.913062+07:00",
        "end": "2025-06-08T23:08:23.91394125+07:00",
        "duration": 998209791,
        "wait": 879250,
        "requests": 600,
        "rate": 601.0760517575409,
        "throughput": 600.547073761767,
        "success": 1,
        "status_codes": {
            "200": 600
        },
        "errors": []
    },
    {
        "latencies": {
            "total": 646428493,
            "mean": 923469,
            "50th": 807919,
            "90th": 1085709,
            "95th": 1292676,
            "99th": 4465603,
            "max": 7280208,
            "min": 567667
        },
        "bytes_in": {
            "total": 123200,
            "mean": 176
        },
        "bytes_out": {
            "total": 123200,
            "mean": 176
        },
        "earliest": "2025-06-08T23:08:23.915644625+07:00",
        "latest": "2025-06-08T23:08:24.914183167+07:00",
        "end": "2025-06-08T23:08:24.915365375+07:00",
        "duration": 998538542,
        "wait": 1182208,
        "requests": 700,
        "rate": 701.0245178898663,
        "throughput": 700.1955296016412,
        "success": 1,
        "status_codes": {
            "200": 700
        },
        "errors": []
    },
    {
        "latencies": {
            "total": 752618343,
            "mean": 940772,
            "50th": 818345,
            "90th": 1117977,
            "95th": 1260640,
            "99th": 3946311,
            "max": 9834792,
            "min": 595709
        },
        "bytes_in": {
            "total": 140800,
            "mean": 176
        },
        "bytes_out": {
            "total": 140800,
            "mean": 176
        },
        "earliest": "2025-06-08T23:08:24.916826708+07:00",
        "latest": "2025-06-08T23:08:25.915703416+07:00",
        "end": "2025-06-08T23:08:25.916479958+07:00",
        "duration": 998876708,
        "wait": 776542,
        "requests": 800,
        "rate": 800.8996441630912,
        "throughput": 800.2774962218149,
        "success": 1,
        "status_codes": {
            "200": 800
        },
        "errors": []
    },
    {
        "latencies": {
            "total": 709630775,
            "mean": 788478,
            "50th": 749687,
            "90th": 908835,
            "95th": 1002926,
            "99th": 1886604,
            "max": 3082584,
            "min": 566166
        },
        "bytes_in": {
            "total": 158400,
            "mean": 176
        },
        "bytes_out": {
            "total": 158400,
            "mean": 176
        },
        "earliest": "2025-06-08T23:08:25.917949334+07:00",
        "latest": "2025-06-08T23:08:26.916728084+07:00",
        "end": "2025-06-08T23:08:26.917446625+07:00",
        "duration": 998778750,
        "wait": 718541,
        "requests": 900,
        "rate": 901.1004689477023,
        "throughput": 900.4526656591008,
        "success": 1,
        "status_codes": {
            "200": 900
        },
        "errors": []
    },
    {
        "latencies": {
            "total": 773064383,
            "mean": 773064,
            "50th": 726766,
            "90th": 925783,
            "95th": 1038612,
            "99th": 1704207,
            "max": 3245333,
            "min": 559750
        },
        "bytes_in": {
            "total": 176000,
            "mean": 176
        },
        "bytes_out": {
            "total": 176000,
            "mean": 176
        },
        "earliest": "2025-06-08T23:08:26.918712875+07:00",
        "latest": "2025-06-08T23:08:27.917604542+07:00",
        "end": "2025-06-08T23:08:27.918289792+07:00",
        "duration": 998891667,
        "wait": 685250,
        "requests": 1000,
        "rate": 1001.109562765028,
        "throughput": 1000.4232620749885,
        "success": 1,
        "status_codes": {
            "200": 1000
        },
        "errors": []
    },
    {
        "latencies": {
            "total": 858360276,
            "mean": 780327,
            "50th": 739170,
            "90th": 920700,
            "95th": 1035020,
            "99th": 1638859,
            "max": 2742209,
            "min": 547583
        },
        "bytes_in": {
            "total": 193600,
            "mean": 176
        },
        "bytes_out": {
            "total": 193600,
            "mean": 176
        },
        "earliest": "2025-06-08T23:08:27.919289708+07:00",
        "latest": "2025-06-08T23:08:28.918376208+07:00",
        "end": "2025-06-08T23:08:28.919077958+07:00",
        "duration": 999086500,
        "wait": 701750,
        "requests": 1100,
        "rate": 1101.0057687697713,
        "throughput": 1100.2329743323148,
        "success": 1,
        "status_codes": {
            "200": 1100
        },
        "errors": []
    },
    {
        "latencies": {
            "total": 1031371909,
            "mean": 859476,
            "50th": 742422,
            "90th": 928076,
            "95th": 1096542,
            "99th": 4085340,
            "max": 12413750,
            "min": 549375
        },
        "bytes_in": {
            "total": 211200,
            "mean": 176
        },
        "bytes_out": {
            "total": 211200,
            "mean": 176
        },
        "earliest": "2025-06-08T23:08:28.920092625+07:00",
        "latest": "2025-06-08T23:08:29.919205625+07:00",
        "end": "2025-06-08T23:08:29.919977417+07:00",
        "duration": 999113000,
        "wait": 771792,
        "requests": 1200,
        "rate": 1201.0653449609804,
        "throughput": 1200.138265529295,
        "success": 1,
        "status_codes": {
            "200": 1200
        },
        "errors": []
    },
    {
        "latencies": {
            "total": 1054429080,
            "mean": 811099,
            "50th": 756361,
            "90th": 941273,
            "95th": 1126657,
            "99th": 2115056,
            "max": 3841292,
            "min": 548542
        },
        "bytes_in": {
            "total": 228800,
            "mean": 176
        },
        "bytes_out": {
            "total": 228800,
            "mean": 176
        },
        "earliest": "2025-06-08T23:08:29.920948875+07:00",
        "latest": "2025-06-08T23:08:30.920163333+07:00",
        "end": "2025-06-08T23:08:30.921039291+07:00",
        "duration": 999214458,
        "wait": 875958,
        "requests": 1300,
        "rate": 1301.0220074297604,
        "throughput": 1299.8824698266083,
        "success": 1,
        "status_codes": {
            "200": 1300
        },
        "errors": []
    },
    {
        "latencies": {
            "total": 1139210846,
            "mean": 813722,
            "50th": 764123,
            "90th": 953292,
            "95th": 1064124,
            "99th": 2110249,
            "max": 5700917,
            "min": 547917
        },
        "bytes_in": {
            "total": 246901,
            "mean": 176.35785714285714
        },
        "bytes_out": {
            "total": 246901,
            "mean": 176.35785714285714
        },
        "earliest": "2025-06-08T23:08:30.921952583+07:00",
        "latest": "2025-06-08T23:08:31.921208083+07:00",
        "end": "2025-06-08T23:08:31.922215+07:00",
        "duration": 999255500,
        "wait": 1006917,
        "requests": 1400,
        "rate": 1401.0430765705069,
        "throughput": 1399.632712582462,
        "success": 1,
        "status_codes": {
            "200": 1400
        },
        "errors": []
    },
    {
        "latencies": {
            "total": 1281092954,
            "mean": 854061,
            "50th": 794113,
            "90th": 1032468,
            "95th": 1211288,
            "99th": 2031177,
            "max": 2876375,
            "min": 543833
        },
        "bytes_in": {
            "total": 265500,
            "mean": 177
        },
        "bytes_out": {
            "total": 265500,
            "mean": 177
        },
        "earliest": "2025-06-08T23:08:31.923074916+07:00",
        "latest": "2025-06-08T23:08:32.922407791+07:00",
        "end": "2025-06-08T23:08:32.923303416+07:00",
        "duration": 999332875,
        "wait": 895625,
        "requests": 1500,
        "rate": 1501.0013555293074,
        "throughput": 1499.6573283004834,
        "success": 1,
        "status_codes": {
            "200": 1500
        },
        "errors": []
    },
    {
        "latencies": {
            "total": 1417109931,
            "mean": 885693,
            "50th": 829605,
            "90th": 1070542,
            "95th": 1270192,
            "99th": 1896111,
            "max": 5161334,
            "min": 539375
        },
        "bytes_in": {
            "total": 283200,
            "mean": 177
        },
        "bytes_out": {
            "total": 283200,
            "mean": 177
        },
        "earliest": "2025-06-08T23:08:32.924556834+07:00",
        "latest": "2025-06-08T23:08:33.923622959+07:00",
        "end": "2025-06-08T23:08:33.924511167+07:00",
        "duration": 999066125,
        "wait": 888208,
        "requests": 1600,
        "rate": 1601.4955967003684,
        "throughput": 1600.0730705369122,
        "success": 1,
        "status_codes": {
            "200": 1600
        },
        "errors": []
    },
    {
        "latencies": {
            "total": 1493025974,
            "mean": 878250,
            "50th": 838755,
            "90th": 1052220,
            "95th": 1183489,
            "99th": 1790790,
            "max": 2724458,
            "min": 558125
        },
        "bytes_in": {
            "total": 300900,
            "mean": 177
        },
        "bytes_out": {
            "total": 300900,
            "mean": 177
        },
        "earliest": "2025-06-08T23:08:33.925288333+07:00",
        "latest": "2025-06-08T23:08:34.924687792+07:00",
        "end": "2025-06-08T23:08:34.925777042+07:00",
        "duration": 999399459,
        "wait": 1089250,
        "requests": 1700,
        "rate": 1701.0215331725528,
        "throughput": 1699.1696005236975,
        "success": 1,
        "status_codes": {
            "200": 1700
        },
        "errors": []
    },
    {
        "latencies": {
            "total": 1884029326,
            "mean": 1046682,
            "50th": 884933,
            "90th": 1232287,
            "95th": 1646464,
            "99th": 5932796,
            "max": 11428208,
            "min": 593417
        },
        "bytes_in": {
            "total": 318600,
            "mean": 177
        },
        "bytes_out": {
            "total": 318600,
            "mean": 177
        },
        "earliest": "2025-06-08T23:08:34.926496791+07:00",
        "latest": "2025-06-08T23:08:35.925887791+07:00",
        "end": "2025-06-08T23:08:35.926634958+07:00",
        "duration": 999391000,
        "wait": 747167,
        "requests": 1800,
        "rate": 1801.0968679926075,
        "throughput": 1799.7513337574687,
        "success": 1,
        "status_codes": {
            "200": 1800
        },
        "errors": []
    },
    {
        "latencies": {
            "total": 1670213677,
            "mean": 879059,
            "50th": 830512,
            "90th": 1031269,
            "95th": 1134056,
            "99th": 2247278,
            "max": 4247208,
            "min": 582625
        },
        "bytes_in": {
            "total": 336300,
            "mean": 177
        },
        "bytes_out": {
            "total": 336300,
            "mean": 177
        },
        "earliest": "2025-06-08T23:08:35.927308792+07:00",
        "latest": "2025-06-08T23:08:36.926762334+07:00",
        "end": "2025-06-08T23:08:36.927526084+07:00",
        "duration": 999453542,
        "wait": 763750,
        "requests": 1900,
        "rate": 1901.0388378812709,
        "throughput": 1899.587234890556,
        "success": 1,
        "status_codes": {
            "200": 1900
        },
        "errors": []
    },
    {
        "latencies": {
            "total": 1871090396,
            "mean": 935545,
            "50th": 842626,
            "90th": 1077208,
            "95th": 1255965,
            "99th": 3802887,
            "max": 8764083,
            "min": 549959
        },
        "bytes_in": {
            "total": 354000,
            "mean": 177
        },
        "bytes_out": {
            "total": 354000,
            "mean": 177
        },
        "earliest": "2025-06-08T23:08:36.928192834+07:00",
        "latest": "2025-06-08T23:08:37.927646167+07:00",
        "end": "2025-06-08T23:08:37.928504625+07:00",
        "duration": 999453333,
        "wait": 858458,
        "requests": 2000,
        "rate": 2001.0939320165335,
        "throughput": 1999.3766123666537,
        "success": 1,
        "status_codes": {
            "200": 2000
        },
        "errors": []
    },
    {
        "latencies": {
            "total": 3334961437,
            "mean": 1588076,
            "50th": 906023,
            "90th": 1666261,
            "95th": 3875839,
            "99th": 19994933,
            "max": 25289458,
            "min": 567250
        },
        "bytes_in": {
            "total": 371700,
            "mean": 177
        },
        "bytes_out": {
            "total": 371700,
            "mean": 177
        },
        "earliest": "2025-06-08T23:08:37.929147209+07:00",
        "latest": "2025-06-08T23:08:38.928645959+07:00",
        "end": "2025-06-08T23:08:38.929523417+07:00",
        "duration": 999498750,
        "wait": 877458,
        "requests": 2100,
        "rate": 2101.0531528928877,
        "throughput": 2099.2102603063904,
        "success": 1,
        "status_codes": {
            "200": 2100
        },
        "errors": []
    },
    {
        "latencies": {
            "total": 1983618434,
            "mean": 901644,
            "50th": 846408,
            "90th": 1092139,
            "95th": 1237174,
            "99th": 2146367,
            "max": 3975625,
            "min": 461917
        },
        "bytes_in": {
            "total": 389400,
            "mean": 177
        },
        "bytes_out": {
            "total": 389400,
            "mean": 177
        },
        "earliest": "2025-06-08T23:08:38.93014625+07:00",
        "latest": "2025-06-08T23:08:39.929608708+07:00",
        "end": "2025-06-08T23:08:39.930290958+07:00",
        "duration": 999462458,
        "wait": 682250,
        "requests": 2200,
        "rate": 2201.1832284349794,
        "throughput": 2199.681688462226,
        "success": 1,
        "status_codes": {
            "200": 2200
        },
        "errors": []
    },
    {
        "latencies": {
            "total": 2079377081,
            "mean": 904076,
            "50th": 856357,
            "90th": 1081925,
            "95th": 1247824,
            "99th": 2201040,
            "max": 3862084,
            "min": 585833
        },
        "bytes_in": {
            "total": 407100,
            "mean": 177
        },
        "bytes_out": {
            "total": 407100,
            "mean": 177
        },
        "earliest": "2025-06-08T23:08:39.930932708+07:00",
        "latest": "2025-06-08T23:08:40.930466208+07:00",
        "end": "2025-06-08T23:08:40.931198+07:00",
        "duration": 999533500,
        "wait": 731792,
        "requests": 2300,
        "rate": 2301.0734507647817,
        "throughput": 2299.389990230712,
        "success": 1,
        "status_codes": {
            "200": 2300
        },
        "errors": []
    },
    {
        "latencies": {
            "total": 2177584679,
            "mean": 907326,
            "50th": 850401,
            "90th": 1075779,
            "95th": 1245571,
            "99th": 2364569,
            "max": 4792959,
            "min": 519792
        },
        "bytes_in": {
            "total": 424800,
            "mean": 177
        },
        "bytes_out": {
            "total": 424800,
            "mean": 177
        },
        "earliest": "2025-06-08T23:08:40.931788417+07:00",
        "latest": "2025-06-08T23:08:41.931372834+07:00",
        "end": "2025-06-08T23:08:41.932065167+07:00",
        "duration": 999584417,
        "wait": 692333,
        "requests": 2400,
        "rate": 2400.997813874483,
        "throughput": 2399.3359837664925,
        "success": 1,
        "status_codes": {
            "200": 2400
        },
        "errors": []
    },
    {
        "latencies": {
            "total": 2578732459,
            "mean": 1031492,
            "50th": 918046,
            "90th": 1310123,
            "95th": 1683728,
            "99th": 3265005,
            "max": 6179708,
            "min": 598042
        },
        "bytes_in": {
            "total": 442500,
            "mean": 177
        },
        "bytes_out": {
            "total": 442500,
            "mean": 177
        },
        "earliest": "2025-06-08T23:08:41.932669792+07:00",
        "latest": "2025-06-08T23:08:42.932237917+07:00",
        "end": "2025-06-08T23:08:42.932922875+07:00",
        "duration": 999568125,
        "wait": 684958,
        "requests": 2500,
        "rate": 2501.080153991505,
        "throughput": 2499.367452586997,
        "success": 1,
        "status_codes": {
            "200": 2500
        },
        "errors": []
    },
    {
        "latencies": {
            "total": 2746045827,
            "mean": 1056171,
            "50th": 890625,
            "90th": 1262013,
            "95th": 1720498,
            "99th": 5039974,
            "max": 15632959,
            "min": 606958
        },
        "bytes_in": {
            "total": 460200,
            "mean": 177
        },
        "bytes_out": {
            "total": 460200,
            "mean": 177
        },
        "earliest": "2025-06-08T23:08:42.933461625+07:00",
        "latest": "2025-06-08T23:08:43.933022584+07:00",
        "end": "2025-06-08T23:08:43.933837584+07:00",
        "duration": 999560959,
        "wait": 815000,
        "requests": 2600,
        "rate": 2601.142007988329,
        "throughput": 2599.022873959329,
        "success": 1,
        "status_codes": {
            "200": 2600
        },
        "errors": []
    },
    {
        "latencies": {
            "total": 2921461482,
            "mean": 1082022,
            "50th": 917513,
            "90th": 1258053,
            "95th": 1584123,
            "99th": 6695740,
            "max": 11709125,
            "min": 561125
        },
        "bytes_in": {
            "total": 477900,
            "mean": 177
        },
        "bytes_out": {
            "total": 477900,
            "mean": 177
        },
        "earliest": "2025-06-08T23:08:43.934328459+07:00",
        "latest": "2025-06-08T23:08:44.933911084+07:00",
        "end": "2025-06-08T23:08:44.935623792+07:00",
        "duration": 999582625,
        "wait": 1712708,
        "requests": 2700,
        "rate": 2701.127383041497,
        "throughput": 2696.5071253358174,
        "success": 1,
        "status_codes": {
            "200": 2700
        },
        "errors": []
    },
    {
        "latencies": {
            "total": 2937446654,
            "mean": 1049088,
            "50th": 954270,
            "90th": 1295660,
            "95th": 1573990,
            "99th": 3172979,
            "max": 7865875,
            "min": 581958
        },
        "bytes_in": {
            "total": 495600,
            "mean": 177
        },
        "bytes_out": {
            "total": 495600,
            "mean": 177
        },
        "earliest": "2025-06-08T23:08:44.936118709+07:00",
        "latest": "2025-06-08T23:08:45.935732792+07:00",
        "end": "2025-06-08T23:08:45.936797834+07:00",
        "duration": 999614083,
        "wait": 1065042,
        "requests": 2800,
        "rate": 2801.0809847703995,
        "throughput": 2798.0997405137236,
        "success": 1,
        "status_codes": {
            "200": 2800
        },
        "errors": []
    },
    {
        "latencies": {
            "total": 2972993316,
            "mean": 1025170,
            "50th": 938475,
            "90th": 1276279,
            "95th": 1563372,
            "99th": 2987292,
            "max": 4363292,
            "min": 563209
        },
        "bytes_in": {
            "total": 513300,
            "mean": 177
        },
        "bytes_out": {
            "total": 513300,
            "mean": 177
        },
        "earliest": "2025-06-08T23:08:45.937304458+07:00",
        "latest": "2025-06-08T23:08:46.936925958+07:00",
        "end": "2025-06-08T23:08:46.93762925+07:00",
        "duration": 999621500,
        "wait": 703292,
        "requests": 2900,
        "rate": 2901.0980656178363,
        "throughput": 2899.058409021217,
        "success": 1,
        "status_codes": {
            "200": 2900
        },
        "errors": []
    },
    {
        "latencies": {
            "total": 3046794488,
            "mean": 1015598,
            "50th": 942296,
            "90th": 1285663,
            "95th": 1473630,
            "99th": 2401048,
            "max": 5282708,
            "min": 585667
        },
        "bytes_in": {
            "total": 531000,
            "mean": 177
        },
        "bytes_out": {
            "total": 531000,
            "mean": 177
        },
        "earliest": "2025-06-08T23:08:46.93811275+07:00",
        "latest": "2025-06-08T23:08:47.937789333+07:00",
        "end": "2025-06-08T23:08:47.938691167+07:00",
        "duration": 999676583,
        "wait": 901834,
        "requests": 3000,
        "rate": 3000.9705648971876,
        "throughput": 2998.265752118457,
        "success": 1,
        "status_codes": {
            "200": 3000
        },
        "errors": []
    },
    {
        "latencies": {
            "total": 3240573586,
            "mean": 1045346,
            "50th": 952364,
            "90th": 1320656,
            "95th": 1631162,
            "99th": 3081541,
            "max": 6070209,
            "min": 574250
        },
        "bytes_in": {
            "total": 548700,
            "mean": 177
        },
        "bytes_out": {
            "total": 548700,
            "mean": 177
        },
        "earliest": "2025-06-08T23:08:47.939151125+07:00",
        "latest": "2025-06-08T23:08:48.938836833+07:00",
        "end": "2025-06-08T23:08:48.9396075+07:00",
        "duration": 999685708,
        "wait": 770667,
        "requests": 3100,
        "rate": 3100.9746115126013,
        "throughput": 3098.5858828677065,
        "success": 1,
        "status_codes": {
            "200": 3100
        },
        "errors": []
    },
    {
        "latencies": {
            "total": 3267010114,
            "mean": 1020940,
            "50th": 953609,
            "90th": 1296428,
            "95th": 1497463,
            "99th": 2628263,
            "max": 4228584,
            "min": 562042
        },
        "bytes_in": {
            "total": 566400,
            "mean": 177
        },
        "bytes_out": {
            "total": 566400,
            "mean": 177
        },
        "earliest": "2025-06-08T23:08:48.940068625+07:00",
        "latest": "2025-06-08T23:08:49.939775834+07:00",
        "end": "2025-06-08T23:08:49.940526792+07:00",
        "duration": 999707209,
        "wait": 750958,
        "requests": 3200,
        "rate": 3200.9372056053667,
        "throughput": 3198.534537026774,
        "success": 1,
        "status_codes": {
            "200": 3200
        },
        "errors": []
    },
    {
        "latencies": {
            "total": 3312029962,
            "mean": 1003645,
            "50th": 944906,
            "90th": 1261248,
            "95th": 1439350,
            "99th": 2313089,
            "max": 4719167,
            "min": 546875
        },
        "bytes_in": {
            "total": 584100,
            "mean": 177
        },
        "bytes_out": {
            "total": 584100,
            "mean": 177
        },
        "earliest": "2025-06-08T23:08:49.940982334+07:00",
        "latest": "2025-06-08T23:08:50.940701417+07:00",
        "end": "2025-06-08T23:08:50.941750042+07:00",
        "duration": 999719083,
        "wait": 1048625,
        "requests": 3300,
        "rate": 3300.9272865905673,
        "throughput": 3297.468507047392,
        "success": 1,
        "status_codes": {
            "200": 3300
        },
        "errors": []
    },
    {
        "latencies": {
            "total": 4480119677,
            "mean": 1317682,
            "50th": 979718,
            "90th": 1511102,
            "95th": 2371281,
            "99th": 12048625,
            "max": 19720583,
            "min": 545250
        },
        "bytes_in": {
            "total": 601800,
            "mean": 177
        },
        "bytes_out": {
            "total": 601800,
            "mean": 177
        },
        "earliest": "2025-06-08T23:08:50.942165083+07:00",
        "latest": "2025-06-08T23:08:51.941859125+07:00",
        "end": "2025-06-08T23:08:51.942899917+07:00",
        "duration": 999694042,
        "wait": 1040792,
        "requests": 3400,
        "rate": 3401.040575572421,
        "throughput": 3397.5033989873086,
        "success": 1,
        "status_codes": {
            "200": 3400
        },
        "errors": []
    },
    {
        "latencies": {
            "total": 4815067942,
            "mean": 1375733,
            "50th": 993493,
            "90th": 1951295,
            "95th": 3446189,
            "99th": 9417445,
            "max": 19337625,
            "min": 552250
        },
        "bytes_in": {
            "total": 619500,
            "mean": 177
        },
        "bytes_out": {
            "total": 619500,
            "mean": 177
        },
        "earliest": "2025-06-08T23:08:51.943306+07:00",
        "latest": "2025-06-08T23:08:52.943022375+07:00",
        "end": "2025-06-08T23:08:52.943866208+07:00",
        "duration": 999716375,
        "wait": 843833,
        "requests": 3500,
        "rate": 3500.99296913087,
        "throughput": 3498.040369800515,
        "success": 1,
        "status_codes": {
            "200": 3500
        },
        "errors": []
    },
    {
        "latencies": {
            "total": 4748682999,
            "mean": 1318712,
            "50th": 1013555,
            "90th": 1771212,
            "95th": 2952177,
            "99th": 7640064,
            "max": 18277125,
            "min": 562000
        },
        "bytes_in": {
            "total": 637377,
            "mean": 177
        },
        "bytes_out": {
            "total": 637377,
            "mean": 177
        },
        "earliest": "2025-06-08T23:08:52.944243542+07:00",
        "latest": "2025-06-08T23:08:53.9442485+07:00",
        "end": "2025-06-08T23:08:53.944977625+07:00",
        "duration": 1000004958,
        "wait": 729125,
        "requests": 3601,
        "rate": 3600.982146330518,
        "throughput": 3598.3585061926988,
        "success": 1,
        "status_codes": {
            "200": 3601
        },
        "errors": []
    },
    {
        "latencies": {
            "total": 4271971994,
            "mean": 1154587,
            "50th": 1016366,
            "90th": 1559418,
            "95th": 1977716,
            "99th": 3851320,
            "max": 7067500,
            "min": 556375
        },
        "bytes_in": {
            "total": 654900,
            "mean": 177
        },
        "bytes_out": {
            "total": 654900,
            "mean": 177
        },
        "earliest": "2025-06-08T23:08:53.945389375+07:00",
        "latest": "2025-06-08T23:08:54.945100792+07:00",
        "end": "2025-06-08T23:08:54.946404917+07:00",
        "duration": 999711417,
        "wait": 1304125,
        "requests": 3700,
        "rate": 3701.068065325496,
        "throughput": 3696.246306633269,
        "success": 1,
        "status_codes": {
            "200": 3700
        },
        "errors": []
    },
    {
        "latencies": {
            "total": 5303181218,
            "mean": 1395574,
            "50th": 1044169,
            "90th": 1821093,
            "95th": 3086178,
            "99th": 9306504,
            "max": 15863917,
            "min": 579917
        },
        "bytes_in": {
            "total": 672600,
            "mean": 177
        },
        "bytes_out": {
            "total": 672600,
            "mean": 177
        },
        "earliest": "2025-06-08T23:08:54.946814375+07:00",
        "latest": "2025-06-08T23:08:55.946525+07:00",
        "end": "2025-06-08T23:08:55.947433208+07:00",
        "duration": 999710625,
        "wait": 908208,
        "requests": 3800,
        "rate": 3801.0999432960916,
        "throughput": 3797.6498889262857,
        "success": 1,
        "status_codes": {
            "200": 3800
        },
        "errors": []
    },
    {
        "latencies": {
            "total": 4672745587,
            "mean": 1198139,
            "50th": 1059402,
            "90th": 1703160,
            "95th": 2129693,
            "99th": 3498170,
            "max": 8422541,
            "min": 515959
        },
        "bytes_in": {
            "total": 690300,
            "mean": 177
        },
        "bytes_out": {
            "total": 690300,
            "mean": 177
        },
        "earliest": "2025-06-08T23:08:55.94782675+07:00",
        "latest": "2025-06-08T23:08:56.947596959+07:00",
        "end": "2025-06-08T23:08:56.948422292+07:00",
        "duration": 999770209,
        "wait": 825333,
        "requests": 3900,
        "rate": 3900.896390882557,
        "throughput": 3897.678768590796,
        "success": 1,
        "status_codes": {
            "200": 3900
        },
        "errors": []
    },
    {
        "latencies": {
            "total": 4573178635,
            "mean": 1143294,
            "50th": 1026742,
            "90th": 1490336,
            "95th": 1827386,
            "99th": 3489045,
            "max": 8363917,
            "min": 499500
        },
        "bytes_in": {
            "total": 708000,
            "mean": 177
        },
        "bytes_out": {
            "total": 708000,
            "mean": 177
        },
        "earliest": "2025-06-08T23:08:56.94885225+07:00",
        "latest": "2025-06-08T23:08:57.948545625+07:00",
        "end": "2025-06-08T23:08:57.950082125+07:00",
        "duration": 999693375,
        "wait": 1536500,
        "requests": 4000,
        "rate": 4001.226876190912,
        "throughput": 3995.086542938004,
        "success": 1,
        "status_codes": {
            "200": 4000
        },
        "errors": []
    },
    {
        "latencies": {
            "total": 5529715058,
            "mean": 1348710,
            "50th": 1026450,
            "90th": 1601692,
            "95th": 2404702,
            "99th": 10889765,
            "max": 17634708,
            "min": 567750
        },
        "bytes_in": {
            "total": 725700,
            "mean": 177
        },
        "bytes_out": {
            "total": 725700,
            "mean": 177
        },
        "earliest": "2025-06-08T23:08:57.950478833+07:00",
        "latest": "2025-06-08T23:08:58.95026575+07:00",
        "end": "2025-06-08T23:08:58.95102975+07:00",
        "duration": 999786917,
        "wait": 764000,
        "requests": 4100,
        "rate": 4100.873826497572,
        "throughput": 4097.74248400394,
        "success": 1,
        "status_codes": {
            "200": 4100
        },
        "errors": []
    },
    {
        "latencies": {
            "total": 5329295130,
            "mean": 1268879,
            "50th": 1026458,
            "90th": 1636696,
            "95th": 2546236,
            "99th": 6589860,
            "max": 18815042,
            "min": 505042
        },
        "bytes_in": {
            "total": 743400,
            "mean": 177
        },
        "bytes_out": {
            "total": 743400,
            "mean": 177
        },
        "earliest": "2025-06-08T23:08:58.951390916+07:00",
        "latest": "2025-06-08T23:08:59.951145458+07:00",
        "end": "2025-06-08T23:08:59.95237775+07:00",
        "duration": 999754542,
        "wait": 1232292,
        "requests": 4200,
        "rate": 4201.031176710573,
        "throughput": 4195.859383301339,
        "success": 1,
        "status_codes": {
            "200": 4200
        },
        "errors": []
    },
    {
        "latencies": {
            "total": 5165413054,
            "mean": 1201258,
            "50th": 1052239,
            "90th": 1639210,
            "95th": 2049006,
            "99th": 3776966,
            "max": 11252750,
            "min": 547875
        },
        "bytes_in": {
            "total": 761100,
            "mean": 177
        },
        "bytes_out": {
            "total": 761100,
            "mean": 177
        },
        "earliest": "2025-06-08T23:08:59.952727666+07:00",
        "latest": "2025-06-08T23:09:00.952503333+07:00",
        "end": "2025-06-08T23:09:00.963220416+07:00",
        "duration": 999775667,
        "wait": 10717083,
        "requests": 4300,
        "rate": 4300.964848347325,
        "throughput": 4255.349679648864,
        "success": 1,
        "status_codes": {
            "200": 4300
        },
        "errors": []
    },
    {
        "latencies": {
            "total": 5357503001,
            "mean": 1217614,
            "50th": 1064016,
            "90th": 1597333,
            "95th": 2152222,
            "99th": 4671337,
            "max": 7711958,
            "min": 563958
        },
        "bytes_in": {
            "total": 778800,
            "mean": 177
        },
        "bytes_out": {
            "total": 778800,
            "mean": 177
        },
        "earliest": "2025-06-08T23:09:00.963594542+07:00",
        "latest": "2025-06-08T23:09:01.963375125+07:00",
        "end": "2025-06-08T23:09:01.964257959+07:00",
        "duration": 999780583,
        "wait": 882834,
        "requests": 4400,
        "rate": 4400.965646679298,
        "throughput": 4397.08290045343,
        "success": 1,
        "status_codes": {
            "200": 4400
        },
        "errors": []
    },
    {
        "latencies": {
            "total": 6183729720,
            "mean": 1374162,
            "50th": 1130226,
            "90th": 2072448,
            "95th": 2933661,
            "99th": 5714934,
            "max": 10027625,
            "min": 485375
        },
        "bytes_in": {
            "total": 800002,
            "mean": 177.7782222222222
        },
        "bytes_out": {
            "total": 800002,
            "mean": 177.7782222222222
        },
        "earliest": "2025-06-08T23:09:01.964621333+07:00",
        "latest": "2025-06-08T23:09:02.964385208+07:00",
        "end": "2025-06-08T23:09:02.965346666+07:00",
        "duration": 999763875,
        "wait": 961458,
        "requests": 4500,
        "rate": 4501.062813456828,
        "throughput": 4496.7383672698525,
        "success": 1,
        "status_codes": {
            "200": 4500
        },
        "errors": []
    },
    {
        "latencies": {
            "total": 8951362154,
            "mean": 1945948,
            "50th": 1186679,
            "90th": 2821880,
            "95th": 4942605,
            "99th": 18268390,
            "max": 27640792,
            "min": 558750
        },
        "bytes_in": {
            "total": 818800,
            "mean": 178
        },
        "bytes_out": {
            "total": 818800,
            "mean": 178
        },
        "earliest": "2025-06-08T23:09:02.965690291+07:00",
        "latest": "2025-06-08T23:09:03.965512666+07:00",
        "end": "2025-06-08T23:09:03.966484375+07:00",
        "duration": 999822375,
        "wait": 971709,
        "requests": 4600,
        "rate": 4600.81722015873,
        "throughput": 4596.350111917728,
        "success": 1,
        "status_codes": {
            "200": 4600
        },
        "errors": []
    },
    {
        "latencies": {
            "total": 6949102897,
            "mean": 1478532,
            "50th": 1134850,
            "90th": 2119822,
            "95th": 3102261,
            "99th": 9625928,
            "max": 18815166,
            "min": 552500
        },
        "bytes_in": {
            "total": 836600,
            "mean": 178
        },
        "bytes_out": {
            "total": 836600,
            "mean": 178
        },
        "earliest": "2025-06-08T23:09:03.966829875+07:00",
        "latest": "2025-06-08T23:09:04.966610792+07:00",
        "end": "2025-06-08T23:09:04.967509667+07:00",
        "duration": 999780917,
        "wait": 898875,
        "requests": 4700,
        "rate": 4701.029915737029,
        "throughput": 4696.807148075196,
        "success": 1,
        "status_codes": {
            "200": 4700
        },
        "errors": []
    },
    {
        "latencies": {
            "total": 6747305215,
            "mean": 1405688,
            "50th": 1136714,
            "90th": 2049967,
            "95th": 2933903,
            "99th": 6349521,
            "max": 16443042,
            "min": 517583
        },
        "bytes_in": {
            "total": 854400,
            "mean": 178
        },
        "bytes_out": {
            "total": 854400,
            "mean": 178
        },
        "earliest": "2025-06-08T23:09:04.967890708+07:00",
        "latest": "2025-06-08T23:09:05.9676325+07:00",
        "end": "2025-06-08T23:09:05.9686465+07:00",
        "duration": 999741792,
        "wait": 1014000,
        "requests": 4800,
        "rate": 4801.239718505236,
        "throughput": 4796.374938192713,
        "success": 1,
        "status_codes": {
            "200": 4800
        },
        "errors": []
    },
    {
        "latencies": {
            "total": 8104661606,
            "mean": 1654012,
            "50th": 1300042,
            "90th": 2793834,
            "95th": 3886710,
            "99th": 6634211,
            "max": 10858792,
            "min": 570542
        },
        "bytes_in": {
            "total": 872200,
            "mean": 178
        },
        "bytes_out": {
            "total": 872200,
            "mean": 178
        },
        "earliest": "2025-06-08T23:09:05.969000667+07:00",
        "latest": "2025-06-08T23:09:06.968835875+07:00",
        "end": "2025-06-08T23:09:06.969982125+07:00",
        "duration": 999835208,
        "wait": 1146250,
        "requests": 4900,
        "rate": 4900.807613888308,
        "throughput": 4895.195571145135,
        "success": 1,
        "status_codes": {
            "200": 4900
        },
        "errors": []
    },
    {
        "latencies": {
            "total": 9012541205,
            "mean": 1802508,
            "50th": 1237935,
            "90th": 3039083,
            "95th": 4882213,
            "99th": 12693002,
            "max": 18957167,
            "min": 538375
        },
        "bytes_in": {
            "total": 890000,
            "mean": 178
        },
        "bytes_out": {
            "total": 890000,
            "mean": 178
        },
        "earliest": "2025-06-08T23:09:06.970295916+07:00",
        "latest": "2025-06-08T23:09:07.970064166+07:00",
        "end": "2025-06-08T23:09:07.971341625+07:00",
        "duration": 999768250,
        "wait": 1277459,
        "requests": 5000,
        "rate": 5001.159018602561,
        "throughput": 4994.776916825083,
        "success": 1,
        "status_codes": {
            "200": 5000
        },
        "errors": []
    }
]